emailverifier/__init__.py
smtp_email_validator-0.1.1.dist-info/licenses/LICENSE
smtp_email_validator-0.1.1.dist-info/METADATA
smtp_email_validator-0.1.1.dist-info/WHEEL
smtp_email_validator-0.1.1.dist-info/top_level.txt
smtp_email_validator-0.1.1.dist-info/RECORD
