Metadata-Version: 2.4
Name: smtp-email-validator
Version: 0.1.1
Summary: Comprehensive email verification tool using regex, MX and SMTP checks
Home-page: https://github.com/Nworah-Gabriel/emailverifier
Author: Nworah Chimzuruoke Gabriel
Author-email: your.email@example.com
Classifier: Programming Language :: Python :: 3
Classifier: License :: OSI Approved :: MIT License
Classifier: Operating System :: OS Independent
Requires-Python: >=3.7
License-File: LICENSE
Requires-Dist: dnspython
Dynamic: author
Dynamic: author-email
Dynamic: classifier
Dynamic: description
Dynamic: description-content-type
Dynamic: home-page
Dynamic: license-file
Dynamic: requires-dist
Dynamic: requires-python
Dynamic: summary
